{"stats":{"minecraft:used":{"unkomod:unko_block":6,"unkomod:unko":7},"minecraft:picked_up":{"unkomod:unko":5},"minecraft:custom":{"minecraft:jump":10,"minecraft:time_since_rest":14966,"minecraft:leave_game":1,"minecraft:damage_dealt":9,"minecraft:sprint_one_cm":285,"minecraft:play_time":14966,"minecraft:time_since_death":14966,"minecraft:walk_one_cm":7124,"minecraft:total_world_time":155845,"minecraft:mob_kills":1,"minecraft:drop":5,"minecraft:fly_one_cm":3408},"minecraft:dropped":{"unkomod:unko":5}},"DataVersion":3337}